openpyxl_utils/__init__.py
openpyxl_utils/adder.py
openpyxl_utils/py.typed
openpyxl_utils/reader.py
openpyxl_utils/remover.py
openpyxl_utils/updater.py
openpyxl_utils/utils.py
openpyxl_utils-0.0.3.dist-info/licenses/LICENSE
openpyxl_utils-0.0.3.dist-info/METADATA
openpyxl_utils-0.0.3.dist-info/WHEEL
openpyxl_utils-0.0.3.dist-info/top_level.txt
openpyxl_utils-0.0.3.dist-info/RECORD
