Metadata-Version: 2.4
Name: openpyxl-utils
Version: 0.0.3
Summary: Funções utilitárias para facilitar o uso da biblioteca openpyxl.
Author-email: Witor Oliveira <witoredson@gmail.com>
License: MIT
Project-URL: Homepage, https://github.com/Drarlian/openpyxl-utils
Project-URL: Source, https://github.com/Drarlian/openpyxl-utils
Project-URL: Issues, https://github.com/Drarlian/openpyxl-utils/issues
Requires-Python: >=3.8
License-File: LICENSE
Requires-Dist: openpyxl>=3.1.0
Dynamic: license-file
